{
  "_schema": "template-version/1.0",
  "template_version": "2.36.0",
  "released_at": "2026-05-04",
  "compatible_from": "2.0.0",
  "summary": "Atlas canon upstream + parité Notion + frictions runtime · (1) Atlas brand (sense 4) inscrit canonique upstream pour cartographie holistique data e-commerce · lexicon.md passe à 4 senses MECE, doctrine atlas-brand.md créée (~750 mots, 9 sections), atlas-canon-copy.md disclaimer disambiguation, canon.md entry, capabilities.md mention, 4 SKILL.md disclaimers patchés (3 → 4 senses) · (2) /phantom cockpit enrichi pour parité Notion · 5 nouveaux modes (briefs / tests / matrix / atlas / doctrine) + 2 drills produits (mechanisms / benefits) + 3 patches gaps existants (profile-audience next-suggested · INDEX.md bridge · smart-suggest daemon slot) · phantom.md split append-only vers phantom-modes/canon.md + phantom-modes/item.md (cap 1000 respecté) · (3) Frictions runtime test live v2.35 résolues · compose-creative v1.0.2 (HR3 payload aspect_ratio explicit nano-banana-pro/edit + HR3.4 retry adaptative scène complexe + HR3.5 post-gen crop PIL fallback), produce-paid-angles v1.4.0 (HR4.5 verbatim density floor AskUserQuestion explicit gate). Manifest skills regenerated. Backward compat strict additif.",
  "manifest": "docs/internal/releases/manifest/2.36.0-manifest.json"
}
